fail2ban_importer/__init__.py
fail2ban_importer/__main__.py
fail2ban_importer/downloaders/__init__.py
fail2ban_importer/downloaders/http.py
fail2ban_importer/downloaders/s3.py
fail2ban_importer/fail2ban_types.py
fail2ban_importer/utils.py
fail2ban_importer-0.0.9.dist-info/entry_points.txt
fail2ban_importer-0.0.9.dist-info/WHEEL
fail2ban_importer-0.0.9.dist-info/METADATA
fail2ban_importer-0.0.9.dist-info/RECORD
