Metadata-Version: 2.1
Name: fail2ban-importer
Version: 0.0.9
Summary: Takes banlists and uses fail2ban to block them
License: MIT
Author: James Hodgkinson
Author-email: james@terminaloutcomes.com
Requires-Python: >=3.8,<4.0
Classifier: License :: OSI Approved :: MIT License
Classifier: Programming Language :: Python :: 3
Classifier: Programming Language :: Python :: 3.10
Classifier: Programming Language :: Python :: 3.8
Classifier: Programming Language :: Python :: 3.9
Requires-Dist: boto3 (>=1.21.37,<2.0.0)
Requires-Dist: click (>=8.1.2,<9.0.0)
Requires-Dist: pydantic (>=1.9.0,<2.0.0)
Requires-Dist: requests (>=2.27.1,<3.0.0)
Requires-Dist: schedule (>=1.1.0,<2.0.0)
